libmypyc_3008ade48759eacf732e.cp36-win_amd64.pyd
mypy/__init__.cp36-win_amd64.pyd
mypy/__init__.py
mypy/__main__.py
mypy/api.cp36-win_amd64.pyd
mypy/api.py
mypy/applytype.cp36-win_amd64.pyd
mypy/applytype.py
mypy/argmap.cp36-win_amd64.pyd
mypy/argmap.py
mypy/binder.cp36-win_amd64.pyd
mypy/binder.py
mypy/bogus_type.py
mypy/build.cp36-win_amd64.pyd
mypy/build.py
mypy/checker.cp36-win_amd64.pyd
mypy/checker.py
mypy/checkexpr.cp36-win_amd64.pyd
mypy/checkexpr.py
mypy/checkmember.cp36-win_amd64.pyd
mypy/checkmember.py
mypy/checkstrformat.cp36-win_amd64.pyd
mypy/checkstrformat.py
mypy/constraints.cp36-win_amd64.pyd
mypy/constraints.py
mypy/defaults.cp36-win_amd64.pyd
mypy/defaults.py
mypy/dmypy.py
mypy/dmypy_os.cp36-win_amd64.pyd
mypy/dmypy_os.py
mypy/dmypy_server.cp36-win_amd64.pyd
mypy/dmypy_server.py
mypy/dmypy_util.cp36-win_amd64.pyd
mypy/dmypy_util.py
mypy/erasetype.cp36-win_amd64.pyd
mypy/erasetype.py
mypy/errors.cp36-win_amd64.pyd
mypy/errors.py
mypy/expandtype.cp36-win_amd64.pyd
mypy/expandtype.py
mypy/exprtotype.cp36-win_amd64.pyd
mypy/exprtotype.py
mypy/fastparse.cp36-win_amd64.pyd
mypy/fastparse.py
mypy/fastparse2.cp36-win_amd64.pyd
mypy/fastparse2.py
mypy/find_sources.cp36-win_amd64.pyd
mypy/find_sources.py
mypy/fixup.cp36-win_amd64.pyd
mypy/fixup.py
mypy/fscache.cp36-win_amd64.pyd
mypy/fscache.py
mypy/fswatcher.cp36-win_amd64.pyd
mypy/fswatcher.py
mypy/gclogger.py
mypy/git.cp36-win_amd64.pyd
mypy/git.py
mypy/indirection.cp36-win_amd64.pyd
mypy/indirection.py
mypy/infer.cp36-win_amd64.pyd
mypy/infer.py
mypy/interpreted_plugin.py
mypy/ipc.cp36-win_amd64.pyd
mypy/ipc.py
mypy/join.cp36-win_amd64.pyd
mypy/join.py
mypy/literals.cp36-win_amd64.pyd
mypy/literals.py
mypy/lookup.cp36-win_amd64.pyd
mypy/lookup.py
mypy/main.py
mypy/maptype.cp36-win_amd64.pyd
mypy/maptype.py
mypy/meet.cp36-win_amd64.pyd
mypy/meet.py
mypy/memprofile.py
mypy/message_registry.cp36-win_amd64.pyd
mypy/message_registry.py
mypy/messages.cp36-win_amd64.pyd
mypy/messages.py
mypy_mypyc-0.670.dist-info/LICENSE
mypy_mypyc-0.670.dist-info/METADATA
mypy_mypyc-0.670.dist-info/WHEEL
mypy_mypyc-0.670.dist-info/entry_points.txt
mypy_mypyc-0.670.dist-info/top_level.txt
mypy_mypyc-0.670.dist-info/RECORD
