Metadata-Version: 2.1
Name: mypy-mypyc
Version: 0.670
Summary: Optional static typing for Python
Home-page: http://www.mypy-lang.org/
Author: Jukka Lehtosalo
Author-email: jukka.lehtosalo@iki.fi
License: MIT License
Platform: UNKNOWN
Classifier: Development Status :: 3 - Alpha
Classifier: Environment :: Console
Classifier: Intended Audience :: Developers
Classifier: License :: OSI Approved :: MIT License
Classifier: Programming Language :: Python :: 3
Classifier: Programming Language :: Python :: 3.4
Classifier: Programming Language :: Python :: 3.5
Classifier: Programming Language :: Python :: 3.6
Classifier: Programming Language :: Python :: 3.7
Classifier: Topic :: Software Development
Provides-Extra: dmypy
